scuff/__init__.py
scuff/__main__.py
scuff/cli.py
scuff/compiler.py
scuff/error.py
scuff/lexer.py
scuff/parser.py
scuff/token.py
scuff/tools.py
scuff-0.4.5.dist-info/LICENSE
scuff-0.4.5.dist-info/METADATA
scuff-0.4.5.dist-info/WHEEL
scuff-0.4.5.dist-info/top_level.txt
scuff-0.4.5.dist-info/RECORD
