Metadata-Version: 2.1
Name: scuff
Version: 0.4.5
Summary: A slick config file format for humans.
Home-page: https://github.com/akyuute/scuff
Author: akyuute
License: MIT
Project-URL: GitHub: repo, https://github.com/akyuute/scuff
Keywords: config files,config file format,data serialization language,parsing,compilers,API,AST,structured data
Platform: Platform Independent
Classifier: Development Status :: 3 - Alpha
Classifier: Environment :: Console
Classifier: Intended Audience :: End Users/Desktop
Classifier: License :: OSI Approved :: MIT License
Classifier: Natural Language :: English
Classifier: Operating System :: OS Independent
Classifier: Programming Language :: Python :: 3
Classifier: Programming Language :: Python :: 3.12
Classifier: Topic :: Software Development :: Libraries :: Python Modules
Classifier: Topic :: Text Processing :: Markup
Classifier: Topic :: Utilities
Requires-Python: >=3.12
License-File: LICENSE
